varq/__init__.py
varq/job.py
varq/structure.py
varq/uniprot.py
varq/varq.py
varq_py-0.3.1.dist-info/LICENSE
varq_py-0.3.1.dist-info/METADATA
varq_py-0.3.1.dist-info/WHEEL
varq_py-0.3.1.dist-info/top_level.txt
varq_py-0.3.1.dist-info/RECORD
