Metadata-Version: 2.1
Name: varq-py
Version: 0.3.1
Summary: VarQ API wrapper for Python.
Home-page: https://gitlab.com/glyco1/varq-py
Author: Mauro Song
Author-email: tik@lag.party
License: UNKNOWN
Platform: UNKNOWN
Classifier: Programming Language :: Python :: 3
Classifier: License :: OSI Approved :: MIT License
Classifier: Operating System :: OS Independent
Classifier: Topic :: Scientific/Engineering :: Bio-Informatics
Requires-Python: >=3.6
Requires-Dist: requests
Requires-Dist: dataclasses
Requires-Dist: dataclasses-json
